dhcpkit_vpp/__init__.py
dhcpkit_vpp/vpp_papi.py
dhcpkit_vpp/listeners/__init__.py
dhcpkit_vpp/listeners/vpp/__init__.py
dhcpkit_vpp/listeners/vpp/component.xml
dhcpkit_vpp/listeners/vpp/config.py
dhcpkit_vpp/listeners/vpp/vpp.py
dhcpkit_vpp/listeners/vpp/vpp_interface.py
dhcpkit_vpp/protocols/__init__.py
dhcpkit_vpp/protocols/layer2.py
dhcpkit_vpp/protocols/layer3.py
dhcpkit_vpp/protocols/layer3_registry.py
dhcpkit_vpp/protocols/layer4.py
dhcpkit_vpp/protocols/layer4_registry.py
dhcpkit_vpp/protocols/utils.py
dhcpkit_vpp/tests/__init__.py
dhcpkit_vpp/tests/protocols/__init__.py
dhcpkit_vpp/tests/protocols/test_base_classes.py
dhcpkit_vpp/tests/protocols/test_layer2.py
dhcpkit_vpp/tests/protocols/test_layer3.py
dhcpkit_vpp/tests/protocols/test_layer4.py
dhcpkit_vpp-1.0.1.dist-info/DESCRIPTION.rst
dhcpkit_vpp-1.0.1.dist-info/METADATA
dhcpkit_vpp-1.0.1.dist-info/RECORD
dhcpkit_vpp-1.0.1.dist-info/WHEEL
dhcpkit_vpp-1.0.1.dist-info/entry_points.txt
dhcpkit_vpp-1.0.1.dist-info/metadata.json
dhcpkit_vpp-1.0.1.dist-info/top_level.txt
